README
setup.py
beatract/__init__.py
beatract/beat_cqt.py
beatract/beat_tie.py
beatract.egg-info/PKG-INFO
beatract.egg-info/SOURCES.txt
beatract.egg-info/dependency_links.txt
beatract.egg-info/requires.txt
beatract.egg-info/top_level.txt