Metadata-Version: 1.0
Name: beatract
Version: 1.4.0
Summary: Beat Extracting module for music
Home-page: https://github.com/Tok-TokPlay/Tok-BeatExtractor
Author: Hyun Joon Choi
Author-email: chj878194@naver.com
License: UNKNOWN
Platform: UNKNOWN
